pynyairbnb/__init__.py
pynyairbnb/data_preprocessing.py
pynyairbnb/plotting.py
pynyairbnb/pynyairbnb.py
pynyairbnb-0.4.0.dist-info/LICENSE
pynyairbnb-0.4.0.dist-info/METADATA
pynyairbnb-0.4.0.dist-info/WHEEL
pynyairbnb-0.4.0.dist-info/RECORD
