Metadata-Version: 2.1
Name: pynyairbnb
Version: 0.4.0
Summary: A package for DSCI 310 Group's Airbnb Analysis.
License: MIT
Author: DSCI 310 Group 9
Requires-Python: >=3.9
Classifier: License :: OSI Approved :: MIT License
Classifier: Programming Language :: Python :: 3
Classifier: Programming Language :: Python :: 3.9
Classifier: Programming Language :: Python :: 3.10
Classifier: Programming Language :: Python :: 3.11
Classifier: Programming Language :: Python :: 3.12
Requires-Dist: click (>=8.1.7)
Requires-Dist: matplotlib (>=3.8.3)
Requires-Dist: numpy (>=1.26.4)
Requires-Dist: pandas (>=2.2.1)
Requires-Dist: scikit-learn (>=1.4.1.post1)
Requires-Dist: scipy (>=1.12.0)
Requires-Dist: seaborn (>=0.13.2)
